flame_pytorch/__init__.py
flame_pytorch/config.py
flame_pytorch/flame.py
FLAME_PyTorch-0.0.1.dist-info/LICENSE
FLAME_PyTorch-0.0.1.dist-info/METADATA
FLAME_PyTorch-0.0.1.dist-info/WHEEL
FLAME_PyTorch-0.0.1.dist-info/top_level.txt
FLAME_PyTorch-0.0.1.dist-info/RECORD
