Metadata-Version: 2.1
Name: FLAME-PyTorch
Version: 0.0.1
Summary: PyTorch implementation of the 3D FLAME model.
Home-page: https://github.com/soubhiksanyal/FLAME_PyTorch
Author: Soubhik Sanyal
Author-email: soubhik.sanyal@tuebingen.mpg.de
License: See LICENSE
Project-URL: Source, https://github.com/soubhiksanyal/FLAME_PyTorch
Keywords: FLAME,3D Face Modelling
Platform: UNKNOWN
Classifier: Natural Language :: English
Classifier: Programming Language :: Python :: 3
Requires-Python: >=3.8
Requires-Dist: numpy (==1.23.4)
Requires-Dist: torch
Requires-Dist: torchvision
Requires-Dist: chumpy (==0.70)
Requires-Dist: pyrender (==0.1.39)
Requires-Dist: trimesh (==3.6.18)
Requires-Dist: smplx
